adaptive_consistency
