Metadata-Version: 2.1
Name: AdaptiveConsistency
Version: 1.0.0
Summary: Library for running AdapativeConsistency based Inference on large language models.
License: MIT
License-File: LICENSE
